README.txt
setup.py
src/pathmunge.py
src/nose_pathmunge.egg-info/PKG-INFO
src/nose_pathmunge.egg-info/SOURCES.txt
src/nose_pathmunge.egg-info/dependency_links.txt
src/nose_pathmunge.egg-info/entry_points.txt
src/nose_pathmunge.egg-info/top_level.txt