Metadata-Version: 1.0
Name: nose-pathmunge
Version: 0.1.2
Summary: Add additional directories to sys.path for nose.
Home-page: UNKNOWN
Author: Jesse Noller
Author-email: jnoller@gmail.com
License: Apache License, Version 2.0
Platform: UNKNOWN
Classifier: Development Status :: 3 - Alpha
Classifier: Intended Audience :: Developers
Classifier: License :: OSI Approved :: Apache Software License
Classifier: Topic :: Software Development :: Testing
